basic_uncenter/__init__.py
basic_uncenter-0.3.3.1.1.1.1.2.dist-info/WHEEL
basic_uncenter-0.3.3.1.1.1.1.2.dist-info/METADATA
basic_uncenter-0.3.3.1.1.1.1.2.dist-info/RECORD
